loopy/__init__.py
loopy/core.py
loopy/core_v2.py
loopy/file_store.py
loopy/shell.py
loopy_fs-0.2.3.dist-info/METADATA
loopy_fs-0.2.3.dist-info/WHEEL
loopy_fs-0.2.3.dist-info/RECORD
