Metadata-Version: 2.4
Name: loopy-fs
Version: 0.2.3
Summary: A filesystem-like API over a tree stored as a string
Project-URL: Homepage, https://github.com/tg1482/loopy
Project-URL: Repository, https://github.com/tg1482/loopy
Author-email: Tanmay Gupta <tg1482@stern.nyu.edu>
License: MIT
Keywords: agents,data-structure,filesystem,llm,tree
Classifier: Development Status :: 4 - Beta
Classifier: Intended Audience :: Developers
Classifier: License :: OSI Approved :: MIT License
Classifier: Programming Language :: Python :: 3
Classifier: Programming Language :: Python :: 3.10
Classifier: Programming Language :: Python :: 3.11
Classifier: Programming Language :: Python :: 3.12
Classifier: Programming Language :: Python :: 3.13
Classifier: Topic :: Software Development :: Libraries :: Python Modules
Requires-Python: >=3.10
